adaptive_harmony/__init__.py
adaptive_harmony/logging_table.py
adaptive_harmony/metric_logger.py
adaptive_harmony/py.typed
adaptive_harmony/common/__init__.py
adaptive_harmony/common/callbacks.py
adaptive_harmony/common/checkpointing.py
adaptive_harmony/common/dpo.py
adaptive_harmony/common/env_grpo.py
adaptive_harmony/common/grpo.py
adaptive_harmony/common/gspo.py
adaptive_harmony/common/ppo.py
adaptive_harmony/common/rm.py
adaptive_harmony/common/sft.py
adaptive_harmony/core/__init__.py
adaptive_harmony/core/dataset.py
adaptive_harmony/core/display.py
adaptive_harmony/core/image_utils.py
adaptive_harmony/core/reasoning.py
adaptive_harmony/core/rich_counter.py
adaptive_harmony/core/rl_utils.py
adaptive_harmony/core/schedulers.py
adaptive_harmony/core/structured_output.py
adaptive_harmony/core/utils.py
adaptive_harmony/core/reward_client/__init__.py
adaptive_harmony/core/reward_client/client.py
adaptive_harmony/core/reward_client/reward_types.py
adaptive_harmony/core/reward_client/websocket_utils.py
adaptive_harmony/environment/__init__.py
adaptive_harmony/environment/environment.py
adaptive_harmony/evaluation/__init__.py
adaptive_harmony/evaluation/evaluation_artifact.py
adaptive_harmony/graders/__init__.py
adaptive_harmony/graders/base_grader.py
adaptive_harmony/graders/combined_grader.py
adaptive_harmony/graders/exceptions.py
adaptive_harmony/graders/reward_server_grader.py
adaptive_harmony/graders/templated_prompt_judge.py
adaptive_harmony/graders/utils.py
adaptive_harmony/graders/answer_relevancy_judge/__init__.py
adaptive_harmony/graders/answer_relevancy_judge/answer_relevancy_judge.py
adaptive_harmony/graders/answer_relevancy_judge/prompts.py
adaptive_harmony/graders/binary_judge/__init__.py
adaptive_harmony/graders/binary_judge/binary_judge.py
adaptive_harmony/graders/binary_judge/prompts.py
adaptive_harmony/graders/context_relevancy_judge/__init__.py
adaptive_harmony/graders/context_relevancy_judge/context_relevancy_judge.py
adaptive_harmony-0.1.24.dist-info/METADATA
adaptive_harmony-0.1.24.dist-info/WHEEL
adaptive_harmony-0.1.24.dist-info/top_level.txt
adaptive_harmony-0.1.24.dist-info/RECORD
