Metadata-Version: 2.4
Name: adaptive-harmony
Version: 0.1.24
Summary: Adaptive Harmony training recipes and utilities for LLM fine-tuning
Classifier: Programming Language :: Python :: 3.12
Classifier: Programming Language :: Python :: 3.13
Classifier: Programming Language :: Python :: Implementation :: CPython
Classifier: Programming Language :: Python :: Implementation :: PyPy
Requires-Python: >=3.12
Requires-Dist: harmony-client~=0.1.0
Requires-Dist: rich>=13.7.0
Requires-Dist: datasets>=2.14.0
Requires-Dist: hf-xet>=1.1.2
Requires-Dist: loguru>=0.7.2
Requires-Dist: pydantic-settings>=2.9.1
Requires-Dist: pydantic>=2.10.5
Requires-Dist: pybars3>=0.9.7
Requires-Dist: pysbd>=0.3.4
Requires-Dist: websockets>=15.0.1
Requires-Dist: setproctitle>=1.3.3
Requires-Dist: pydantic-xml>=2.16.0
Requires-Dist: openai>=1.42.0
Requires-Dist: pillow>=11.3.0
Requires-Dist: boto3>=1.40
Requires-Dist: tomli>=2
Provides-Extra: tensorboard
Requires-Dist: tensorboardX>=2.6.2.2; extra == "tensorboard"
Provides-Extra: mlflow
Requires-Dist: mlflow>=3.4.0; extra == "mlflow"
Provides-Extra: wandb
Requires-Dist: wandb>=0.19.11; extra == "wandb"
Provides-Extra: all-monitoring
Requires-Dist: tensorboardX>=2.6.2.2; extra == "all-monitoring"
Requires-Dist: mlflow>=3.4.0; extra == "all-monitoring"
Requires-Dist: wandb>=0.19.11; extra == "all-monitoring"
Provides-Extra: mlflow-skinny
Requires-Dist: mlflow-skinny>=3.4.0; extra == "mlflow-skinny"
